makepymodule/__init__.py
makepymodule/cli.py
makepymodule/data/setup.template
makepymodule-1.0.5.dist-info/LICENSE
makepymodule-1.0.5.dist-info/METADATA
makepymodule-1.0.5.dist-info/WHEEL
makepymodule-1.0.5.dist-info/entry_points.txt
makepymodule-1.0.5.dist-info/top_level.txt
makepymodule-1.0.5.dist-info/RECORD
