Metadata-Version: 2.1
Name: makepymodule
Version: 1.0.5
Summary: CLI program to generate python module directory structure
Home-page: https://github.com/arvind-iyer/makepymodule
Author: Arvind Iyer
Author-email: arvindi.me@gmail.com
License: UNKNOWN
Platform: UNKNOWN
Classifier: Programming Language :: Python :: 3
Classifier: License :: OSI Approved
Classifier: License :: OSI Approved :: Apache Software License
Classifier: Operating System :: POSIX :: Linux
Classifier: Operating System :: POSIX
